Metadata-Version: 2.1
Name: my-calculator
Version: 0.7
Summary: Several calculations of two numbers
Home-page: https://github.com/ghimireadarsh/My-Calculator.git
Author: Adarsh Ghimire
License: UNKNOWN
Platform: UNKNOWN
